{"schema_version":"1.0.0","elements":[{"description":"<lazy-image> is a custom element that contains an image that has the\noption to be loaded only on-demand, for performance reasons.","summary":"","path":"../../lazy-image.js","properties":[],"methods":[{"name":"_maybeLoadImage","description":"","privacy":"protected","sourceRange":{"start":{"line":62,"column":2},"end":{"line":70,"column":3}},"metadata":{},"params":[]},{"name":"attributeChangedCallback","description":"","privacy":"public","sourceRange":{"start":{"line":74,"column":2},"end":{"line":77,"column":3}},"metadata":{},"params":[{"name":"attr"},{"name":"oldValue"},{"name":"newValue"}]}],"demos":[],"metadata":{},"sourceRange":{"start":{"line":4,"column":0},"end":{"line":78,"column":1}},"privacy":"public","name":"LazyImage","attributes":[{"name":"active","description":"","sourceRange":{"start":{"line":73,"column":44},"end":{"line":73,"column":52}},"metadata":{}},{"name":"src","description":"","sourceRange":{"start":{"line":73,"column":54},"end":{"line":73,"column":59}},"metadata":{}},{"name":"alt","description":"","sourceRange":{"start":{"line":73,"column":61},"end":{"line":73,"column":66}},"metadata":{}}],"events":[],"styling":{"cssVariables":[],"selectors":[]},"slots":[],"tagname":"lazy-image","superclass":"HTMLElement"}]}